{
  "id_plante": "PLT-0143",
  "no_famille": 42.0,
  "famille_fr": "Malvacées",
  "no_espece": "41.3",
  "genre": "Wercklea",
  "espece": "hottensis",
  "nom_scientifique": "Wercklea hottensis",
  "synonymes": "Hibiscus hottensis",
  "nom_francais": "-",
  "nom_creole": "Maho",
  "nom_anglais": "-",
  "forme": "Arbuste",
  "altitude_developpement": "Haute",
  "saveur": "Astringent / Doux",
  "type_usage": "Medicinale",
  "parties_utilisees": "Feuilles, racines",
  "usages_ethnobotaniques": "Anti‑inflammatoire, antidiarrhéique, cicatrisant, analgésique, antioxydant (Haïti, Hispaniola)",
  "usage_haiti": "On prépare une infusion des feuilles contre la grippe.",
  "usage_ailleurs_international": "Endémique : Hotte.",
  "mode_preparation": "Décoction",
  "systemes_concernes": "Respiratoire",
  "maladies": "✅ Poux (Externe)",
  "profil_medicinal": "Données très limitées ; espèce surtout mentionnée dans la flore d’Haïti comme plante de plaies et de diarrhée ; preuves essentiellement ethnobotaniques",
  "mecanisme_action": "Mécanismes supposés : astringence (tanins), activité antioxydante des flavonoïdes, effet anti‑inflammatoire général ; pas d’études COX/α‑glucosidase spécifiques",
  "posologie_documentee": "Posologies (infusion 5 g/L, décoction 2 g/j) sont purement traditionnelles, non validées",
  "toxique": "Inconnu",
  "toxicite_precautions": "Risque de troubles digestifs et d’irritation muqueuse à forte dose ; éviter grossesse/allaitement faute de données",
  "profil_nutritionnel": "Plante non alimentaire",
  "metabolites_primaires": "Glucides, fibres, un peu de protéines/lipides",
  "micro_elements": "Micro‑éléments non caractérisés",
  "metabolites_secondaires": "Flavonoïdes, saponines, tanins, triterpènes, alcaloïdes (profil Malvaceae)",
  "composes_secondaires_defense_couleur": "Mucilages",
  "principaux_constituants_5_cles": "Mucilages, Fibres, Tanins, Cellulose, Inconnu",
  "roles_pour_plantes": "Structure",
  "valeur_locale_haiti": "Artisanat",
  "valeur_internationale": "Botanique",
  "lacunes_donnees_recherche": "Manque d’études cliniques humaines",
  "potentiel_valorisation": "Médicinale + Alimentaire",
  "nombre_articles": -5.0,
  "mode_reproduction": "Graines",
  "indice_abondance": "Rare",
  "statut_origine": "Endémique",
  "besoin_conservation_action": "Urgence de conservation ",
  "tags_systemes": null,
  "tags_maladies": null,
  "tags_substances": null,
  "tags_usages": null,
  "lien_pubmed": "https://pubmed.ncbi.nlm.nih.gov/?term=Wercklea hottensis",
  "lien_tramil": "https://www.tramil.net",
  "lien_gen": "https://www.gbif.org/species/search?taxon_key=Wercklea hottensis",
  "references_liens_1": "PMC + PubMed",
  "references_liens_2": "Google Scholar",
  "lien": "Lien",
  "habitat": "",
  "carte_distribution": "",
  "lien_image": ""
}